{"sections":{"main":{"type":"blog","disabled":true,"settings":{"grid_columns":"3","articles_per_page":12,"grid_gap":8,"show_tags":true,"show_excerpt":true,"show_date":true,"show_author":false,"image_ratio":100,"enable_hover_zoom":true}},"brand_story_g6wHpi":{"type":"brand-story","blocks":{"value_tw3qBL":{"type":"value","settings":{"title":"Innovation","description":"Toutes innovations prends son temps pour arriver."}},"value_UGQTEd":{"type":"value","settings":{"title":"Identité","description":"Chaque détail compte pour s'affirmer devant le miroir ou devant les caméras."}},"value_GerJk9":{"type":"value","settings":{"title":"Durabilité","description":"Notre engagement pour un avenir plus durable, bien que nous pensons à l'écologie, nous pensons aussi à l'héritage."}}},"block_order":["value_tw3qBL","value_UGQTEd","value_GerJk9"],"name":"Brand Story","settings":{"hero_title":"OFFSIDE","hero_subtitle":"DEPUIS QUAND LE SPORT N'EST PLUS CONSIDÉRÉ COMME UN ART ?","hero_note":"Une création de 2025.","story_eyebrow":"OFFSIDE","story_title":"Des histoires à dormir debout, des idées qui n'éclairent personne, des intentions fausses..","story_content":"<p>Qui vas vous mentir pour une histoire d'image et de branding ?<br\/>- <strong>  Celui qui souhaite maquiller ces intentions.<\/strong><\/p><p>Aujourd'hui nous pronons la clarté, la franchise et la simplicité dans les idées complexes.<br\/><br\/>Notre projet est avant tout un défi personnel animé par une petite équipe d'optimistes, les gains, la réalisation et la passion pour un sport nous a unis afin de vous fournir tout une manière de penser !<br\/>Tout un écosystème !<\/p><p><em><strong>- OFFSIDE<\/strong><\/em><\/p><p>Par des inspirations du Streetwear aux Maisons de Luxe on a imaginé tout un musée de produits, toute une vitrine, tout un dressing.<\/p><p>Les habits sportifs nous fascinent mais le quotidien du sportif aussi.<\/p><h2><em><strong>OFFSIDE<\/strong><\/em><\/h2><h3><em><strong>Beyond the rules, not the game.<\/strong><\/em><\/h3>"}}},"order":["main","brand_story_g6wHpi"]}